drone_capability_parser/__init__.py
drone_capability_parser/main.py
drone_capability_parser/prompts.py
drone_capability_parser-2025.12.21140812.dist-info/METADATA
drone_capability_parser-2025.12.21140812.dist-info/WHEEL
drone_capability_parser-2025.12.21140812.dist-info/top_level.txt
drone_capability_parser-2025.12.21140812.dist-info/RECORD
