Metadata-Version: 2.4
Name: drone-capability-parser
Version: 2025.12.21140812
Summary: A new package processes textual descriptions of drone designs to extract structured summaries of their operational capabilities. It focuses on identifying and categorizing key features such as locomot
Author-email: drone-capability-parser <hi@eugene.plus>
License: MIT
Project-URL: Homepage, https://github.com/chigwell/drone-capability-parser
Requires-Python: >=3.9
Requires-Dist: langchain-llm7>=0.0.0
Requires-Dist: llmatch-messages>=0.0.0
Requires-Dist: langchain-core>=0.3.0
